{
    "country": {
        "af": "อัฟกานิสถาน",
        "ax": "หมู่เกาะโอลันด์",
        "al": "แอลเบเนีย",
        "dz": "แอลจีเรีย",
        "as": "อเมริกันซามัว",
        "ad": "อันดอร์รา",
        "ao": "แองโกลา",
        "ai": "แองกวิลลา",
        "aq": "แอนตาร์กติกา",
        "ag": "แอนติกาและบาร์บูดา",
        "ar": "อาร์เจนตินา",
        "am": "อาร์เมเนีย",
        "aw": "อารูบา",
        "au": "ออสเตรเลีย",
        "at": "ออสเตรีย",
        "az": "อาเซอร์ไบจาน",
        "bs": "บาฮามาส",
        "bh": "บาห์เรน",
        "bd": "บังคลาเทศ",
        "bb": "บาร์เบโดส",
        "by": "เบลารุส",
        "be": "เบลเยียม",
        "bz": "เบลีซ",
        "bj": "เบนิน",
        "bm": "เบอร์มิวดา",
        "bt": "ภูฏาน",
        "bo": "โบลิเวีย",
        "ba": "บอสเนียและเฮอร์เซโก",
        "bw": "บอตสวานา",
        "bv": "เกาะบูเวต",
        "br": "บราซิล",
        "io": "บริติชอินเดียนโอเชียนเทร์ริทอรี",
        "bn": "บรูไนดารุสซาลาม",
        "bg": "บัลแกเรีย",
        "bf": "บูร์กินาฟาโซ",
        "bi": "บุรุนดี",
        "kh": "กัมพูชา",
        "cm": "แคเมอรูน",
        "ca": "แคนาดา",
        "cv": "เคปเวิร์ด",
        "ky": "หมู่เกาะเคย์แมน",
        "cf": "สาธารณรัฐแอฟริกากลาง",
        "td": "ชาด",
        "cl": "ชิลี",
        "cn": "จีน",
        "cx": "เกาะคริสต์มาส",
        "cc": "หมู่เกาะโคโคส (คีลิง)",
        "co": "โคลอมเบีย",
        "km": "คอโมโรส",
        "cg": "คองโก",
        "cd": "คองโก สาธารณรัฐประชาธิปไตย",
        "ck": "หมู่เกาะคุก",
        "cr": "คอสตาริกา",
        "ci": "โกตดิวัวร์",
        "hr": "โครเอเชีย",
        "cu": "คิวบา",
        "cy": "ไซปรัส",
        "cz": "สาธารณรัฐเช็ก",
        "dk": "เดนมาร์ก",
        "dj": "จิบูตี",
        "dm": "โดมินิกา",
        "do": "สาธารณรัฐโดมินิกัน",
        "ec": "เอกวาดอร์",
        "eg": "อียิปต์",
        "sv": "เอลซัลวาดอร์",
        "gq": "อิเควทอเรียลกินี",
        "er": "เอริเทรีย",
        "ee": "เอสโตเนีย",
        "et": "เอธิโอเปีย",
        "fk": "หมู่เกาะฟอล์กแลนด์ (มัลวินาส)",
        "fo": "หมู่เกาะแฟโร",
        "fj": "ฟิจิ",
        "fi": "ฟินแลนด์",
        "fr": "ฝรั่งเศส",
        "gf": "เฟรนช์เกีย",
        "pf": "เฟรนช์โปลินีเซีย",
        "tf": "ดินแดนทางใต้ของฝรั่งเศส",
        "ga": "กาบอง",
        "gm": "แกมเบีย",
        "ge": "จอร์เจีย",
        "de": "เยอรมนี",
        "gh": "กานา",
        "gi": "ยิบรอลตาร์",
        "gr": "กรีซ",
        "gl": "กรีนแลนด์",
        "gd": "เกรเนดา",
        "gp": "กวาเดอลูป",
        "gu": "กวม",
        "gt": "กัวเตมาลา",
        "gg": "เสื้อไหมพรม",
        "gn": "กินี",
        "gw": "กินี-บิสเซา",
        "gy": "กายอานา",
        "ht": "เฮติ",
        "hm": "เกาะเฮิร์ดและหมู่เกาะแมคโดนัลด์",
        "va": "นครรัฐวาติกัน",
        "hn": "ฮอนดูรัส",
        "hk": "ฮ่องกง",
        "hu": "ฮังการี",
        "is": "ไอซ์แลนด์",
        "in": "อินเดีย",
        "id": "อินโดนีเซีย",
        "ir": "อิหร่าน สาธารณรัฐอิสลาม",
        "iq": "อิรัก",
        "ie": "ไอร์แลนด์",
        "im": "เกาะแมน",
        "il": "อิสราเอล",
        "it": "อิตาลี",
        "jm": "จาไมก้า",
        "jp": "ญี่ปุ่น",
        "je": "เจอร์ซีย์",
        "jo": "จอร์แดน",
        "kz": "คาซัคสถาน",
        "ke": "เคนยา",
        "ki": "คิริบาส",
        "kr": "เกาหลีใต้",
        "kp": "เกาหลีเหนือ",
        "kw": "คูเวต",
        "kg": "คีร์กีซสถาน",
        "la": "สาธารณรัฐประชาธิปไตยประชาชนลาว",
        "lv": "ลัตเวีย",
        "lb": "เลบานอน",
        "ls": "เลโซโท",
        "lr": "ไลบีเรีย",
        "ly": "ลิเบีย",
        "li": "ลิกเตนสไตน์",
        "lt": "ลิทัวเนีย",
        "lu": "ลักเซมเบิร์ก",
        "mo": "มาเก๊า",
        "mk": "ประเทศมาซิโดเนียเหนือ",
        "mg": "มาดากัสการ์",
        "mw": "มาลาวี",
        "my": "มาเลเซีย",
        "mv": "มัลดีฟส์",
        "ml": "มาลี",
        "mt": "มอลตา",
        "mh": "หมู่เกาะมาร์แชลล์",
        "mq": "มาร์ตินีก",
        "mr": "มอริเตเนีย",
        "mu": "มอริเชียส",
        "yt": "มายอต",
        "mx": "เม็กซิโก",
        "fm": "ไมโครนีเซีย สหพันธรัฐ",
        "md": "มอลโดวา",
        "mc": "โมนาโก",
        "mn": "มองโกเลีย",
        "me": "มอนเตเนโกร",
        "ms": "มอนต์เซอร์รัต",
        "ma": "โมร็อกโก",
        "mz": "โมซัมบิก",
        "mm": "พม่า",
        "na": "นามิเบีย",
        "nr": "นาอูรู",
        "np": "เนปาล",
        "nl": "เนเธอร์แลนด์",
        "an": "เนเธอร์แลนด์",
        "nc": "นิวแคลิโดเนีย",
        "nz": "นิวซีแลนด์",
        "ni": "นิการากัว",
        "ne": "ไนเจอร์",
        "ng": "ไนจีเรีย",
        "nu": "นีอูเอ",
        "nf": "เกาะนอร์ฟอล์ก",
        "mp": "หมู่เกาะนอร์เทิร์นมาเรียนา",
        "no": "นอร์เวย์",
        "om": "โอมาน",
        "pk": "ปากีสถาน",
        "pw": "ปาเลา",
        "ps": "ปาเลสไตน์",
        "pa": "ปานามา",
        "pg": "ปาปัวนิวกินี",
        "py": "ประเทศปารากวัย",
        "pe": "เปรู",
        "ph": "ฟิลิปปินส์",
        "pn": "หมู่เกาะพิตแคร์น",
        "pl": "โปแลนด์",
        "pt": "โปรตุเกส",
        "pr": "เปอร์โตริโก้",
        "qa": "กาตาร์",
        "re": "เรอูว์นียง",
        "ro": "โรมาเนีย",
        "ru": "รัสเซีย",
        "rw": "รวันดา",
        "bl": "นักบุญบาร์เธเลมี",
        "sh": "เซนต์เฮเลนา",
        "kn": "เซนต์คิตส์และเนวิส",
        "lc": "เซนต์ลูเซีย",
        "mf": "เซนต์มาร์ติน",
        "pm": "แซงปีแยร์และมีเกอลง",
        "vc": "เซนต์วินเซนต์และเกรนาดีนส์",
        "ws": "ซามัว",
        "sm": "ซานมารีโน",
        "st": "เซาตูเมและปรินซิปี",
        "sa": "ซาอุดิอาราเบีย",
        "sn": "เซเนกัล",
        "rs": "เซอร์เบีย",
        "sc": "เซเชลส์",
        "sl": "เซียร์ราลีโอน",
        "sg": "สิงคโปร์",
        "sk": "สโลวาเกีย",
        "si": "สโลวีเนีย",
        "sb": "หมู่เกาะโซโลมอน",
        "so": "โซมาเลีย",
        "za": "แอฟริกาใต้",
        "gs": "เกาะเซาท์จอร์เจียและหมู่เกาะเซาท์แซนด์วิช",
        "es": "สเปน",
        "lk": "ศรีลังกา",
        "sd": "ซูดาน",
        "sr": "ซูรินาเม",
        "sj": "สฟาลบาร์และยานไมเอน",
        "sz": "สวาซิแลนด์",
        "se": "สวีเดน",
        "ch": "สวิตเซอร์แลนด์",
        "sy": "สาธารณรัฐอาหรับซีเรีย",
        "tw": "ไต้หวัน",
        "tj": "ทาจิกิสถาน",
        "tz": "แทนซาเนีย",
        "th": "ประเทศไทย",
        "tl": "ติมอร์-เลสเต",
        "tg": "โตโก",
        "tk": "โตเกเลา",
        "to": "ตองกา",
        "tt": "ตรินิแดดและโตเบโก",
        "tn": "ตูนิเซีย",
        "tr": "ประเทศตุรกี",
        "tm": "เติร์กเมนิสถาน",
        "tc": "หมู่เกาะเติกส์และหมู่เกาะเคคอส",
        "tv": "ตูวาลู",
        "ug": "ยูกันดา",
        "ua": "ยูเครน",
        "ae": "สหรัฐอาหรับเอมิเรตส์",
        "gb": "ประเทศอังกฤษ",
        "us": "สหรัฐ",
        "um": "หมู่เกาะรอบนอกของสหรัฐอเมริกา",
        "uy": "อุรุกวัย",
        "uz": "อุซเบกิสถาน",
        "vu": "วานูอาตู",
        "ve": "เวเนซุเอลา",
        "vn": "เวียดนาม",
        "vg": "หมู่เกาะเวอร์จิน อังกฤษ",
        "vi": "หมู่เกาะเวอร์จิน สหรัฐอเมริกา",
        "wf": "วาลลิสและฟุตูนา",
        "eh": "ซาฮาร่าตะวันตก",
        "ye": "เยเมน",
        "zm": "แซมเบีย",
        "zw": "ซิมบับเว",
        "bq": "โบแนร์",
        "cw": "คูราเซา",
        "ss": "ซูดานใต้",
        "ww": "ทั่วโลก",
        "sx": "ซินต์มาร์เติน"
    }
}