{
    "country": {
        "af": "אפגניסטן",
        "ax": "איי אלנד",
        "al": "אלבניה",
        "dz": "אלג'יריה",
        "as": "סמואה האמריקנית",
        "ad": "אנדורה",
        "ao": "אנגולה",
        "ai": "אנגווילה",
        "aq": "אנטארקטיקה",
        "ag": "אנטיגואה וברבודה",
        "ar": "ארגנטינה",
        "am": "ארמניה",
        "aw": "ארובה",
        "au": "אוסטרליה",
        "at": "אוסטריה",
        "az": "אזרבייג'ן",
        "bs": "איי בהאמה",
        "bh": "בחריין",
        "bd": "בנגלדש",
        "bb": "ברבדוס",
        "by": "בלארוס",
        "be": "בלגיה",
        "bz": "בליז",
        "bj": "בנין",
        "bm": "ברמודה",
        "bt": "בהוטן",
        "bo": "בוליביה",
        "ba": "בוסניה והרצגובינה",
        "bw": "בוצואנה",
        "bv": "האי בובה",
        "br": "ברזיל",
        "io": "טריטוריית האוקיינוס ההודי הבריטי",
        "bn": "ברוניי דארוסלאם",
        "bg": "בולגריה",
        "bf": "בורקינה פאסו",
        "bi": "בורונדי",
        "kh": "קמבודיה",
        "cm": "קמרון",
        "ca": "קנדה",
        "cv": "קייפ ורדה",
        "ky": "איי קיימן",
        "cf": "הרפובליקה המרכז - אפריקאית",
        "td": "צ'אד",
        "cl": "צ'ילה",
        "cn": "חרסינה",
        "cx": "אי חג המולד",
        "cc": "איי קוקוס (קילינג)",
        "co": "קולומביה",
        "km": "קומורו",
        "cg": "קונגו",
        "cd": "קונגו, הרפובליקה הדמוקרטית",
        "ck": "איי קוק",
        "cr": "קוסטה ריקה",
        "ci": "חוף השנהב",
        "hr": "קרואטיה",
        "cu": "קובה",
        "cy": "קַפרִיסִין",
        "cz": "הרפובליקה הצ'כית",
        "dk": "דנמרק",
        "dj": "ג'יבוטי",
        "dm": "דומיניקה",
        "do": "הרפובליקה הדומיניקנית",
        "ec": "אקוודור",
        "eg": "מִצְרַיִם",
        "sv": "אל סלבדור",
        "gq": "גיניאה המשוונית",
        "er": "אריתריאה",
        "ee": "אסטוניה",
        "et": "אתיופיה",
        "fk": "איי פוקלנד (מלווינאס)",
        "fo": "איי פרו",
        "fj": "פיג'י",
        "fi": "פינלנד",
        "fr": "צרפת",
        "gf": "גיאנה הצרפתית",
        "pf": "פולינזיה הצרפתית",
        "tf": "השטחים הדרומיים של צרפת",
        "ga": "גאבון",
        "gm": "גמביה",
        "ge": "גאורגיה",
        "de": "גרמניה",
        "gh": "גאנה",
        "gi": "גיברלטר",
        "gr": "יון",
        "gl": "גרינלנד",
        "gd": "גרנדה",
        "gp": "גוואדלופ",
        "gu": "גואם",
        "gt": "גואטמלה",
        "gg": "גרנזי",
        "gn": "גינאה",
        "gw": "גינאה-ביסאו",
        "gy": "גיאנה",
        "ht": "האיטי",
        "hm": "האי הרד ואיי מקדונלד",
        "va": "קריית הוותיקן (הכס הקדוש)",
        "hn": "הונדורס",
        "hk": "הונג קונג",
        "hu": "הונגריה",
        "is": "איסלנד",
        "in": "הוֹדוּ",
        "id": "אינדונזיה",
        "ir": "איראן",
        "iq": "עִירַאק",
        "ie": "אירלנד",
        "im": "האי מאן",
        "il": "ישראל",
        "it": "איטליה",
        "jm": "ג'מייקה",
        "jp": "יפן",
        "je": "ג'רזי",
        "jo": "ירדן",
        "kz": "קזחסטן",
        "ke": "קניה",
        "ki": "קיריבטי",
        "kr": "דרום קוריאה",
        "kp": "צפון קוריאה",
        "kw": "כווית",
        "kg": "קירגיזסטן",
        "la": "הרפובליקה הדמוקרטית העממית של לאו",
        "lv": "לטביה",
        "lb": "לבנון",
        "ls": "לסוטו",
        "lr": "ליבריה",
        "ly": "לוב",
        "li": "ליכטנשטיין",
        "lt": "ליטא",
        "lu": "לוקסמבורג",
        "mo": "מקאו",
        "mk": "מקדוניה הצפונית",
        "mg": "מדגסקר",
        "mw": "מלאווי",
        "my": "מלזיה",
        "mv": "המלדיביים",
        "ml": "מלי",
        "mt": "מלטה",
        "mh": "איי מרשל",
        "mq": "מרטיניק",
        "mr": "מאוריטניה",
        "mu": "מאוריציוס",
        "yt": "מיוט",
        "mx": "מקסיקו",
        "fm": "מיקרונזיה",
        "md": "מולדובה",
        "mc": "מונקו",
        "mn": "מונגוליה",
        "me": "מונטנגרו",
        "ms": "מונטסראט",
        "ma": "מרוקו",
        "mz": "מוזמביק",
        "mm": "מיאנמר",
        "na": "נמיביה",
        "nr": "נאורו",
        "np": "נפאל",
        "nl": "הולנד",
        "an": "האנטילים ההולנדיים",
        "nc": "קלדוניה החדשה",
        "nz": "ניו זילנד",
        "ni": "ניקרגואה",
        "ne": "ניז'ר",
        "ng": "ניגריה",
        "nu": "ניואה",
        "nf": "האי נורפוק",
        "mp": "איי מריאנה הצפוניים",
        "no": "נורווגיה",
        "om": "עומאן",
        "pk": "פקיסטן",
        "pw": "פלאו",
        "ps": "מדינה פלסטינית",
        "pa": "פנמה",
        "pg": "פפואה גינאה החדשה",
        "py": "פרגוואי",
        "pe": "פרו",
        "ph": "פיליפינים",
        "pn": "איי פיטקרן",
        "pl": "פּוֹלִין",
        "pt": "פּוֹרטוּגָל",
        "pr": "פוארטו ריקו",
        "qa": "קטאר",
        "re": "ראוניון",
        "ro": "רומניה",
        "ru": "רוסיה",
        "rw": "רואנדה",
        "bl": "סנט ברתלמי",
        "sh": "סנט הלנה",
        "kn": "סנט קיטס ונוויס",
        "lc": "סנט לוסיה",
        "mf": "מרטין הקדוש",
        "pm": "סנט פייר ומיקלון",
        "vc": "סנט וינסנט וגרנדינים",
        "ws": "סמואה",
        "sm": "סן מרינו",
        "st": "סאו טומה ופרינסיפה",
        "sa": "ערב הסעודית",
        "sn": "סנגל",
        "rs": "סרביה",
        "sc": "איי סיישל",
        "sl": "סיירה לאון",
        "sg": "סינגפור",
        "sk": "סלובקיה",
        "si": "סלובניה",
        "sb": "איי שלמה",
        "so": "סומליה",
        "za": "דרום אפריקה",
        "gs": "איי ג'ורג'יה הדרומית ואיי סנדוויץ' הדרומיים",
        "es": "ספרד",
        "lk": "סרי לנקה",
        "sd": "סודן",
        "sr": "סורינאם",
        "sj": "סבאלברד ויאן מאיין",
        "sz": "סווזילנד",
        "se": "שבדיה",
        "ch": "שוויץ",
        "sy": "הרפובליקה הערבית של סוריה",
        "tw": "טייוואן",
        "tj": "טג'יקיסטן",
        "tz": "טנזניה",
        "th": "תאילנד",
        "tl": "טימור-לסטה",
        "tg": "טוגו",
        "tk": "טוקלאו",
        "to": "טונגה",
        "tt": "טרינידד וטובגו",
        "tn": "תוניסיה",
        "tr": "טורקיה",
        "tm": "טורקמניסטן",
        "tc": "איי טורקס וקאיקוס",
        "tv": "טובאלו",
        "ug": "אוגנדה",
        "ua": "אוקראינה",
        "ae": "איחוד האמירויות הערביות",
        "gb": "הממלכה המאוחדת",
        "us": "ארצות הברית",
        "um": "האיים המרוחקים של ארצות הברית",
        "uy": "אורוגוואי",
        "uz": "אוזבקיסטן",
        "vu": "ונואטו",
        "ve": "ונצואלה",
        "vn": "וייטנאם",
        "vg": "איי הבתולה, הבריטים",
        "vi": "איי הבתולה, ארה\"ב",
        "wf": "וואליס ופוטונה",
        "eh": "סהרה המערבית",
        "ye": "תימן",
        "zm": "זמביה",
        "zw": "זימבבואה",
        "bq": "בונייר",
        "cw": "קוראסאו",
        "ss": "דרום סודן",
        "ww": "בעולם כולו",
        "sx": "סנט מארטן"
    }
}