{
    "country": {
        "af": "Afghanistan",
        "ax": "Visiwa vya Aland",
        "al": "Albania",
        "dz": "Algeria",
        "as": "Samoa ya Marekani",
        "ad": "Andora",
        "ao": "Angola",
        "ai": "Anguilla",
        "aq": "Antaktika",
        "ag": "Antigua na Barbuda",
        "ar": "Argentina",
        "am": "Armenia",
        "aw": "Aruba",
        "au": "Australia",
        "at": "Austria",
        "az": "Azerbaijan",
        "bs": "Bahamas",
        "bh": "Bahrain",
        "bd": "Bangladesh",
        "bb": "Barbados",
        "by": "Belarus",
        "be": "Ubelgiji",
        "bz": "Belize",
        "bj": "Benin",
        "bm": "Bermuda",
        "bt": "Bhutan",
        "bo": "Bolivia",
        "ba": "Bosnia na Herzegovina",
        "bw": "Botswana",
        "bv": "Kisiwa cha Bouvet",
        "br": "Brazili",
        "io": "Eneo la Bahari ya Hindi la Uingereza",
        "bn": "Brunei Darussalam",
        "bg": "Bulgaria",
        "bf": "Burkina Faso",
        "bi": "Burundi",
        "kh": "Kambodia",
        "cm": "Kamerun",
        "ca": "Kanada",
        "cv": "Cabo Verde",
        "ky": "Visiwa vya Cayman",
        "cf": "Jamhuri ya Afrika ya Kati",
        "td": "Chad",
        "cl": "Chile",
        "cn": "China",
        "cx": "Kisiwa cha Krismasi",
        "cc": "Visiwa vya Cocos (Keeling)",
        "co": "Kolombia",
        "km": "Komoro",
        "cg": "Kongo",
        "cd": "Kongo, Jamhuri ya Kidemokrasia",
        "ck": "Visiwa vya Cook",
        "cr": "Kosta Rika",
        "ci": "Côte d'Ivoire",
        "hr": "Kroatia",
        "cu": "Kuba",
        "cy": "Kupro",
        "cz": "Jamhuri ya Czech",
        "dk": "Denmark",
        "dj": "Djibouti",
        "dm": "Dominika",
        "do": "Jamhuri ya Dominika",
        "ec": "Ekuador",
        "eg": "Misri",
        "sv": "El Salvador",
        "gq": "Guinea ya Ikweta",
        "er": "Eritrea",
        "ee": "Estonia",
        "et": "Ethiopia",
        "fk": "Visiwa vya Falkland (Malvinas)",
        "fo": "Visiwa vya Faroe",
        "fj": "Fiji",
        "fi": "Ufini",
        "fr": "Ufaransa",
        "gf": "Guiana ya Ufaransa",
        "pf": "Polynesia ya Ufaransa",
        "tf": "Wilaya za Kusini mwa Ufaransa",
        "ga": "Gabon",
        "gm": "Gambia",
        "ge": "Georgia",
        "de": "Ujerumani",
        "gh": "Ghana",
        "gi": "Gibraltar",
        "gr": "Ugiriki",
        "gl": "Greenland",
        "gd": "Grenada",
        "gp": "Guadeloupe",
        "gu": "Guam",
        "gt": "Guatemala",
        "gg": "Guernsey",
        "gn": "Guinea",
        "gw": "Guinea-Bissau",
        "gy": "Guyana",
        "ht": "Haiti",
        "hm": "Visiwa vya Heard na Visiwa vya McDonald",
        "va": "Vatikani",
        "hn": "Honduras",
        "hk": "Hong Kong",
        "hu": "Hungaria",
        "is": "Iceland",
        "in": "India",
        "id": "Indonesia",
        "ir": "Iran, Jamhuri ya Kiislamu ya",
        "iq": "Iraq",
        "ie": "Eire",
        "im": "Kisiwa cha Man",
        "il": "Israel",
        "it": "Italia",
        "jm": "Jamaika",
        "jp": "Japani",
        "je": "Jersey",
        "jo": "Yordani",
        "kz": "Kazakhstan",
        "ke": "Kenya",
        "ki": "Kiribati",
        "kr": "Korea Kusini",
        "kp": "Korea Kaskazini",
        "kw": "Kuwait",
        "kg": "Kyrgyzstan",
        "la": "Laos",
        "lv": "Latvia",
        "lb": "Lebanon",
        "ls": "Lesotho",
        "lr": "Liberia",
        "ly": "Libya",
        "li": "Liechtenstein",
        "lt": "Lithuania",
        "lu": "Luxemburg",
        "mo": "Makao",
        "mk": "Masedonia Kaskazini",
        "mg": "Madagaska",
        "mw": "Malawi",
        "my": "Malaysia",
        "mv": "Maldives",
        "ml": "Mali",
        "mt": "Malta",
        "mh": "Visiwa vya Marshall",
        "mq": "Martinique",
        "mr": "Mauritania",
        "mu": "Mauritius",
        "yt": "Mayotte",
        "mx": "Mexico",
        "fm": "Mikronesia, Majimbo Shirikisho la",
        "md": "Moldova",
        "mc": "Monako",
        "mn": "Mongolia",
        "me": "Montenegro",
        "ms": "Montserrat",
        "ma": "Moroko",
        "mz": "Msumbiji",
        "mm": "Myanmar",
        "na": "Namibia",
        "nr": "Nauru",
        "np": "Nepal",
        "nl": "Uholanzi",
        "an": "Antilles ya Uholanzi",
        "nc": "Kaledonia Mpya",
        "nz": "New Zealand",
        "ni": "Nikaragua",
        "ne": "Niger",
        "ng": "Nigeria",
        "nu": "Niue",
        "nf": "Kisiwa cha Norfolk",
        "mp": "Visiwa vya Mariana ya Kaskazini",
        "no": "Norway",
        "om": "Oman",
        "pk": "Pakistani",
        "pw": "Palau",
        "ps": "Palestina",
        "pa": "Panama",
        "pg": "Papua Guinea Mpya",
        "py": "Paragwai",
        "pe": "Peru",
        "ph": "Ufilipino",
        "pn": "Visiwa vya Pitcairn",
        "pl": "Poland",
        "pt": "Ureno",
        "pr": "Puerto Rico",
        "qa": "Qatar",
        "re": "Réunion",
        "ro": "Rumania",
        "ru": "Urusi",
        "rw": "Rwanda",
        "bl": "Mtakatifu Barthelemy",
        "sh": "Mtakatifu Helena",
        "kn": "Saint Kitts na Nevis",
        "lc": "Mtakatifu Lucia",
        "mf": "Mtakatifu Martin",
        "pm": "Mtakatifu Pierre na Miquelon",
        "vc": "Saint Vincent na Grenadines",
        "ws": "Samoa",
        "sm": "San Marino",
        "st": "Sao Tome na Principe",
        "sa": "Saudi Arabia",
        "sn": "Senegal",
        "rs": "Serbia",
        "sc": "Shelisheli",
        "sl": "Sierra Leone",
        "sg": "Singapore",
        "sk": "Slovakia",
        "si": "Slovenia",
        "sb": "Visiwa vya Solomon",
        "so": "Somalia",
        "za": "Africa Kusini",
        "gs": "Visiwa vya South Georgia na South Sandwich",
        "es": "Uhispania",
        "lk": "Sri Lanka",
        "sd": "Sudan",
        "sr": "Suriname",
        "sj": "Svalbard na Jan Mayen",
        "sz": "Swaziland",
        "se": "Uswidi",
        "ch": "Uswisi",
        "sy": "Jamhuri ya Kiarabu ya Syria",
        "tw": "Taiwan",
        "tj": "Tajikistan",
        "tz": "Tanzania",
        "th": "Thailand",
        "tl": "Timor-Leste",
        "tg": "Togo",
        "tk": "Tokelau",
        "to": "Tonga",
        "tt": "Trinidad na Tobago",
        "tn": "Tunisia",
        "tr": "Uturuki",
        "tm": "Turkmenistan",
        "tc": "Visiwa vya Turks na Caicos",
        "tv": "Tuvalu",
        "ug": "Uganda",
        "ua": "Ukraine",
        "ae": "Umoja wa Falme za Kiarabu",
        "gb": "Uingereza",
        "us": "Marekani",
        "um": "Visiwa vya Nje vya Marekani",
        "uy": "Uruguay",
        "uz": "Uzbekistan",
        "vu": "Vanuatu",
        "ve": "Venezuela",
        "vn": "Vietnam",
        "vg": "Visiwa vya Virgin, Uingereza",
        "vi": "Visiwa vya Virgin, Marekani",
        "wf": "Wallis na Futuna",
        "eh": "Sahara Magharibi",
        "ye": "Yemen",
        "zm": "Zambia",
        "zw": "Zimbabwe",
        "bq": "Bonaire",
        "cw": "Curacao",
        "ss": "Sudan Kusini",
        "ww": "Duniani kote",
        "sx": "Sint Maarten"
    }
}