{
    "notification": {
        "push": {
            "account_recap": {
                "header": "🍺 {name} , Đây là bản tóm tắt hàng tháng của bạn!",
                "body": "Bạn đã có thêm {amount} người ủng hộ mới trong tháng này. Hãy tiếp tục cố gắng nhé!"
            }
        },
        "panel": {
            "account_recap": {
                "body": "Bạn đã có thêm {amount} người ủng hộ mới trong tháng qua trên tất cả các chiến dịch của mình. Hãy tiếp tục làm việc tuyệt vời nhé!",
                "header": "🍺 {name} , Đây là bản tóm tắt hàng tháng của bạn!"
            }
        }
    }
}