{
    "testimonials": {
        "aiesec": {
            "paragraph_2": "Millania a ensuite expliqué qu'elle et son équipe avaient l'habitude de créer un cadre manuellement, où chacun doit entrer et ajuster ses photos dans le cadre manuellement. Avec Twibbonize, elle est en mesure de réaliser une campagne numérique de manière très pratique. Sans oublier que la distribution de la campagne est également perçue comme relativement facile, la seule tâche étant de choisir la photo, et vous aurez votre Twibbon en un rien de temps."
        }
    },
    "general": {
        "relative_time": {
            "seconds": "quelques secondes",
            "future": "en %s",
            "past": "%s il y a",
            "minute": "une minute",
            "minutes": "%d minutes",
            "hour": "une heure",
            "hours": "%d heures",
            "day": "un jour",
            "days": "%d jours",
            "month": "un mois",
            "months": "%d mois",
            "year": "une année",
            "years": "%d années"
        }
    }
}